LICENSE
npss/__init__.py
npss/npss.py
npss-1.0.0.dist-info/entry_points.txt
npss-1.0.0.dist-info/LICENSE
npss-1.0.0.dist-info/WHEEL
npss-1.0.0.dist-info/METADATA
npss-1.0.0.dist-info/RECORD
